Metadata-Version: 2.1
Name: simplequi
Version: 1.0.7
Summary: Run codeskulptor.org programs on the desktop using Qt/PySide2
Home-page: https://github.com/ArthurGW/simplequi
Author: Arthur Gordon-Wright
Author-email: simplequi.codeskulptor@gmail.com
License: GPLv3
Platform: UNKNOWN
Classifier: License :: OSI Approved :: GNU General Public License v3 (GPLv3)
Classifier: Programming Language :: Python :: 3
Classifier: Programming Language :: Python :: 3.5
Classifier: Programming Language :: Python :: 3.6
Classifier: Programming Language :: Python :: 3.7
Requires-Python: >=3.5
Requires-Dist: PySide2 (>=5.12.0)
Provides-Extra: build
Requires-Dist: bump2version (>=0.5.11) ; extra == 'build'
Requires-Dist: wheel (>=0.33.6) ; extra == 'build'
Requires-Dist: setuptools (>=40) ; extra == 'build'
Provides-Extra: dev
Requires-Dist: bump2version (>=0.5.11) ; extra == 'dev'
Requires-Dist: wheel (>=0.33.6) ; extra == 'dev'
Requires-Dist: setuptools (>=40) ; extra == 'dev'
Requires-Dist: sphinx (>=2.2) ; extra == 'dev'
Requires-Dist: sphinx-rtd-theme (>=0.4.3) ; extra == 'dev'
Requires-Dist: sphinx-autodoc-typehints[type_comments] ; extra == 'dev'
Requires-Dist: m2r ; extra == 'dev'
Provides-Extra: docs
Requires-Dist: sphinx (>=2.2) ; extra == 'docs'
Requires-Dist: sphinx-rtd-theme (>=0.4.3) ; extra == 'docs'
Requires-Dist: sphinx-autodoc-typehints[type_comments] ; extra == 'docs'
Requires-Dist: m2r ; extra == 'docs'
